openrouter_observer/__init__.py
openrouter_observer/__main__.py
openrouter_observer/config_loader.py
openrouter_observer/llm_client/__init__.py
openrouter_observer/main.py
openrouter_observer/observer/__init__.py
openrouter_observer/observer/tracker.py
openrouter_observer/store/__init__.py
openrouter_observer/utils/parser.py
openrouter_observer-0.0.1.dist-info/entry_points.txt
openrouter_observer-0.0.1.dist-info/METADATA
openrouter_observer-0.0.1.dist-info/WHEEL
openrouter_observer-0.0.1.dist-info/RECORD
