Metadata-Version: 2.3
Name: openrouter-observer
Version: 0.0.1
Summary: 
Author: Rajesh Marudhachalam
Author-email: rajesh.marudhachalam@gmail.com
Requires-Python: >=3.10,<3.11
Classifier: Programming Language :: Python :: 3
Classifier: Programming Language :: Python :: 3.10
Requires-Dist: colorama (==0.4.6)
Requires-Dist: python-box (==6.1.0)
